LICENSE
MANIFEST.in
Makefile
README.md
pyproject.toml
setup.py
extern/pybind11/include/pybind11/attr.h
extern/pybind11/include/pybind11/buffer_info.h
extern/pybind11/include/pybind11/cast.h
extern/pybind11/include/pybind11/chrono.h
extern/pybind11/include/pybind11/common.h
extern/pybind11/include/pybind11/complex.h
extern/pybind11/include/pybind11/critical_section.h
extern/pybind11/include/pybind11/eigen.h
extern/pybind11/include/pybind11/embed.h
extern/pybind11/include/pybind11/eval.h
extern/pybind11/include/pybind11/functional.h
extern/pybind11/include/pybind11/gil.h
extern/pybind11/include/pybind11/gil_safe_call_once.h
extern/pybind11/include/pybind11/gil_simple.h
extern/pybind11/include/pybind11/iostream.h
extern/pybind11/include/pybind11/native_enum.h
extern/pybind11/include/pybind11/numpy.h
extern/pybind11/include/pybind11/operators.h
extern/pybind11/include/pybind11/options.h
extern/pybind11/include/pybind11/pybind11.h
extern/pybind11/include/pybind11/pytypes.h
extern/pybind11/include/pybind11/stl.h
extern/pybind11/include/pybind11/stl_bind.h
extern/pybind11/include/pybind11/subinterpreter.h
extern/pybind11/include/pybind11/trampoline_self_life_support.h
extern/pybind11/include/pybind11/type_caster_pyobject_ptr.h
extern/pybind11/include/pybind11/typing.h
extern/pybind11/include/pybind11/warnings.h
extern/pybind11/include/pybind11/conduit/pybind11_conduit_v1.h
extern/pybind11/include/pybind11/conduit/pybind11_platform_abi_id.h
extern/pybind11/include/pybind11/conduit/wrap_include_python_h.h
extern/pybind11/include/pybind11/detail/class.h
extern/pybind11/include/pybind11/detail/common.h
extern/pybind11/include/pybind11/detail/cpp_conduit.h
extern/pybind11/include/pybind11/detail/descr.h
extern/pybind11/include/pybind11/detail/dynamic_raw_ptr_cast_if_possible.h
extern/pybind11/include/pybind11/detail/exception_translation.h
extern/pybind11/include/pybind11/detail/function_record_pyobject.h
extern/pybind11/include/pybind11/detail/init.h
tokendagger.egg-info/PKG-INFO
tokendagger.egg-info/SOURCES.txt
tokendagger.egg-info/dependency_links.txt
tokendagger.egg-info/not-zip-safe
tokendagger.egg-info/requires.txt
tokendagger.egg-info/top_level.txt