Metadata-Version: 2.4
Name: tokendagger
Version: 0.1.1
Summary: High-Performance Implementation of OpenAI's TikToken - 2x Throughput, 4x Faster Code Tokenization
Author-email: Your Name <your.email@example.com>
License: MIT License
Project-URL: Homepage, https://github.com/M4THYOU/TokenDagger
Project-URL: Repository, https://github.com/M4THYOU/TokenDagger
Project-URL: Bug Reports, https://github.com/M4THYOU/TokenDagger/issues
Project-URL: Documentation, https://github.com/M4THYOU/TokenDagger#readme
Keywords: tokenization,tiktoken,nlp,text-processing,openai,bpe
Classifier: Development Status :: 4 - Beta
Classifier: Intended Audience :: Developers
Classifier: License :: OSI Approved :: MIT License
Classifier: Programming Language :: Python :: 3
Classifier: Programming Language :: Python :: 3.8
Classifier: Programming Language :: Python :: 3.9
Classifier: Programming Language :: Python :: 3.10
Classifier: Programming Language :: Python :: 3.11
Classifier: Programming Language :: Python :: 3.12
Classifier: Programming Language :: C++
Classifier: Topic :: Text Processing :: Linguistic
Classifier: Topic :: Software Development :: Libraries :: Python Modules
Classifier: Topic :: Scientific/Engineering :: Artificial Intelligence
Requires-Python: >=3.8
License-File: LICENSE
Provides-Extra: dev
Requires-Dist: tiktoken; extra == "dev"
Requires-Dist: pytest; extra == "dev"
Requires-Dist: black; extra == "dev"
Requires-Dist: flake8; extra == "dev"
Dynamic: license-file
Dynamic: requires-python
